groupdocs/metadata/py.typed
aspose/pycore/py.typed
aspose/pycore/__init__.pyi
aspose/pyreflection/py.typed
aspose/pyreflection/__init__.pyi
aspose/pydrawing/py.typed
aspose/pydrawing/__init__.pyi
aspose/pydrawing/design.pyi
aspose/pydrawing/drawing2d.pyi
aspose/pydrawing/imaging.pyi
aspose/pydrawing/printing.pyi
aspose/pydrawing/text.pyi
groupdocs/metadata/__init__.pyi
groupdocs/metadata/common/__init__.pyi
groupdocs/metadata/exceptions/__init__.pyi
groupdocs/metadata/export/__init__.pyi
groupdocs/metadata/formats/__init__.pyi
groupdocs/metadata/formats/archive/__init__.pyi
groupdocs/metadata/formats/audio/__init__.pyi
groupdocs/metadata/formats/audio/ogg/__init__.pyi
groupdocs/metadata/formats/businesscard/__init__.pyi
groupdocs/metadata/formats/cad/__init__.pyi
groupdocs/metadata/formats/document/__init__.pyi
groupdocs/metadata/formats/ebook/__init__.pyi
groupdocs/metadata/formats/ebook/fb2/__init__.pyi
groupdocs/metadata/formats/ebook/mobi/__init__.pyi
groupdocs/metadata/formats/email/__init__.pyi
groupdocs/metadata/formats/fb2/__init__.pyi
groupdocs/metadata/formats/font/__init__.pyi
groupdocs/metadata/formats/gis/__init__.pyi
groupdocs/metadata/formats/image/__init__.pyi
groupdocs/metadata/formats/image/dng/__init__.pyi
groupdocs/metadata/formats/mpeg/__init__.pyi
groupdocs/metadata/formats/peer2peer/__init__.pyi
groupdocs/metadata/formats/raw/__init__.pyi
groupdocs/metadata/formats/raw/cr2/__init__.pyi
groupdocs/metadata/formats/raw/tag/__init__.pyi
groupdocs/metadata/formats/riff/__init__.pyi
groupdocs/metadata/formats/threed/__init__.pyi
groupdocs/metadata/formats/threed/dae/__init__.pyi
groupdocs/metadata/formats/threed/fbx/__init__.pyi
groupdocs/metadata/formats/threed/stl/__init__.pyi
groupdocs/metadata/formats/threed/threeds/__init__.pyi
groupdocs/metadata/formats/video/__init__.pyi
groupdocs/metadata/importing/__init__.pyi
groupdocs/metadata/logging/__init__.pyi
groupdocs/metadata/options/__init__.pyi
groupdocs/metadata/search/__init__.pyi
groupdocs_metadata_net-25.4.dist-info/METADATA
groupdocs_metadata_net-25.4.dist-info/WHEEL
groupdocs_metadata_net-25.4.dist-info/entry_points.txt
groupdocs_metadata_net-25.4.dist-info/top_level.txt
groupdocs_metadata_net-25.4.dist-info/RECORD
